{"objectID":"_ping_updater.html#ping_updater.md","parent":"_ping_updater.html#inputs","pageViews":0,"url":"writerside-documentation/ping-updater.html#ping-updater.md","mainTitle":"Ping Updater dataflow","product":"","headings":"Ping Updater dataflow","content":"The Ping Updater DFL is responsible to update ping/keep-alive messages sent from devices. This is the information you see under device \u0026quot;last seen\u0026quot; indicators in esthesis CORE. Keep-alive, or ping, messages are obtained from Kafka and processed through this plugin to update the esthesis CORE database.\n","pageTitle":"Ping Updater dataflow","metaDescription":"","type":"Documentation","breadcrumbs":"Dataflows","root":0,"depth":1}